[
  [
    {
      "__type__": "cc.Prefab",
      "_name": "GameOverPanel",
      "data": {
        "__id__": 1
      }
    },
    {
      "__type__": "cc.Node",
      "_name": "GameOverPanel",
      "_children": [
        {
          "__id__": 2
        },
        {
          "__id__": 3
        },
        {
          "__id__": 4
        }
      ],
      "_components": [
        {
          "__type__": "cc.Sprite",
          "node": {
            "__id__": 1
          },
          "_spriteFrame": {
            "__uuid__": "a5KjPOxUJFiKrz722h2ivl"
          },
          "_sizeMode": 0
        },
        {
          "__type__": "0ea8a+DihpA4rETWYjkzoR8",
          "node": {
            "__id__": 1
          }
        }
      ],
      "_prefab": {
        "__type__": "cc.PrefabInfo",
        "root": {
          "__id__": 1
        },
        "asset": {
          "__uuid__": "4eoOUPBW5MVot5D/eHRi8x"
        },
        "fileId": "1eHlyZzgZASb8GDumQX1zk"
      },
      "_contentSize": {
        "__type__": "cc.Size",
        "width": 800,
        "height": 500
      },
      "_position": {
        "__type__": "cc.Vec3",
        "x": 480,
        "y": 320
      },
      "_scaleX": 1,
      "_scaleY": 1,
      "_scale": {
        "__type__": "cc.Vec3",
        "x": 1,
        "y": 1,
        "z": 1
      }
    },
    {
      "__type__": "cc.Node",
      "_name": "shelter",
      "_parent": {
        "__id__": 1
      },
      "_components": [
        {
          "__type__": "cc.Sprite",
          "node": {
            "__id__": 2
          },
          "_spriteFrame": {
            "__uuid__": "8c20Sso/ZEn7NUfNSM+EBh"
          },
          "_sizeMode": 0
        },
        {
          "__type__": "cc.Button",
          "node": {
            "__id__": 2
          },
          "_N$target": {
            "__id__": 2
          }
        }
      ],
      "_prefab": {
        "__type__": "cc.PrefabInfo",
        "root": {
          "__id__": 1
        },
        "asset": {
          "__uuid__": "4eoOUPBW5MVot5D/eHRi8x"
        },
        "fileId": "33OTqFlENNJYrVEyFV10pc"
      },
      "_opacity": 0,
      "_color": {
        "__type__": "cc.Color",
        "r": 202,
        "g": 159,
        "b": 159
      },
      "_contentSize": {
        "__type__": "cc.Size",
        "width": 960,
        "height": 640
      },
      "_position": {
        "__type__": "cc.Vec3",
        "x": -2,
        "y": 2
      },
      "_scaleX": 1,
      "_scaleY": 1,
      "_scale": {
        "__type__": "cc.Vec3",
        "x": 1,
        "y": 1,
        "z": 1
      }
    },
    {
      "__type__": "cc.Node",
      "_name": "Label",
      "_parent": {
        "__id__": 1
      },
      "_components": [
        {
          "__type__": "cc.Label",
          "node": {
            "__id__": 3
          },
          "_useOriginalSize": false,
          "_N$overflow": 2
        }
      ],
      "_prefab": {
        "__type__": "cc.PrefabInfo",
        "root": {
          "__id__": 1
        },
        "asset": {
          "__uuid__": "4eoOUPBW5MVot5D/eHRi8x"
        },
        "fileId": "fageKLV/tF+KuPyiOZIZj4"
      },
      "_contentSize": {
        "__type__": "cc.Size",
        "width": 600,
        "height": 350
      },
      "_position": {
        "__type__": "cc.Vec3",
        "y": 16
      },
      "_scaleX": 1,
      "_scaleY": 1,
      "_scale": {
        "__type__": "cc.Vec3",
        "x": 1,
        "y": 1,
        "z": 1
      }
    },
    {
      "__type__": "cc.Node",
      "_name": "Btn",
      "_parent": {
        "__id__": 1
      },
      "_children": [
        {
          "__id__": 5
        }
      ],
      "_components": [
        {
          "__type__": "cc.Sprite",
          "node": {
            "__id__": 4
          },
          "_spriteFrame": {
            "__uuid__": "ce9BNDQl9KE6VmVGBcKjKm"
          },
          "_type": 1,
          "_sizeMode": 0
        },
        {
          "__type__": "cc.Button",
          "node": {
            "__id__": 4
          },
          "_N$transition": 2,
          "transition": 2,
          "_N$normalColor": {
            "__type__": "cc.Color",
            "r": 255,
            "g": 255,
            "b": 255
          },
          "_N$pressedColor": {
            "__type__": "cc.Color",
            "r": 255,
            "g": 255,
            "b": 255
          },
          "pressedColor": {
            "__type__": "cc.Color",
            "r": 255,
            "g": 255,
            "b": 255
          },
          "_N$disabledColor": {
            "__type__": "cc.Color",
            "r": 255,
            "g": 255,
            "b": 255
          },
          "_N$normalSprite": {
            "__uuid__": "ce9BNDQl9KE6VmVGBcKjKm"
          },
          "_N$pressedSprite": {
            "__uuid__": "e97GVMl6JHh5Ml5qEDdSGa"
          },
          "pressedSprite": {
            "__uuid__": "e97GVMl6JHh5Ml5qEDdSGa"
          },
          "_N$hoverSprite": {
            "__uuid__": "e97GVMl6JHh5Ml5qEDdSGa"
          },
          "hoverSprite": {
            "__uuid__": "e97GVMl6JHh5Ml5qEDdSGa"
          },
          "_N$disabledSprite": {
            "__uuid__": "29FYIk+N1GYaeWH/q1NxQO"
          },
          "_N$target": {
            "__id__": 4
          }
        }
      ],
      "_prefab": {
        "__type__": "cc.PrefabInfo",
        "root": {
          "__id__": 1
        },
        "asset": {
          "__uuid__": "4eoOUPBW5MVot5D/eHRi8x"
        },
        "fileId": "b6eMhCCnZDsYk0xEDnP0i/"
      },
      "_contentSize": {
        "__type__": "cc.Size",
        "width": 120,
        "height": 50
      },
      "_position": {
        "__type__": "cc.Vec3",
        "x": 7,
        "y": -192
      },
      "_scaleX": 1,
      "_scaleY": 1,
      "_scale": {
        "__type__": "cc.Vec3",
        "x": 1,
        "y": 1,
        "z": 1
      }
    },
    {
      "__type__": "cc.Node",
      "_name": "Label",
      "_parent": {
        "__id__": 4
      },
      "_components": [
        {
          "__type__": "cc.Label",
          "node": {
            "__id__": 5
          },
          "_useOriginalSize": false,
          "_string": "返回",
          "_N$string": "返回",
          "_enableWrapText": false,
          "_N$horizontalAlign": 1,
          "_N$verticalAlign": 1,
          "_N$overflow": 1
        }
      ],
      "_prefab": {
        "__type__": "cc.PrefabInfo",
        "root": {
          "__id__": 1
        },
        "asset": {
          "__uuid__": "4eoOUPBW5MVot5D/eHRi8x"
        },
        "fileId": "8dgGp0lMhAB7IbR5gH8XoQ"
      },
      "_color": {
        "__type__": "cc.Color"
      },
      "_contentSize": {
        "__type__": "cc.Size",
        "width": 100,
        "height": 40
      },
      "_position": {
        "__type__": "cc.Vec3",
        "x": -1,
        "y": 2
      },
      "_scaleX": 1,
      "_scaleY": 1,
      "_scale": {
        "__type__": "cc.Vec3",
        "x": 1,
        "y": 1,
        "z": 1
      }
    }
  ],
  {
    "__type__": "cc.SpriteFrame",
    "content": {
      "name": "GameOver",
      "texture": "66T9MWjnZNupRa50i6hsNn",
      "rect": [
        0,
        0,
        1024,
        768
      ],
      "offset": [
        0,
        0
      ],
      "originalSize": [
        1024,
        768
      ],
      "capInsets": [
        0,
        0,
        0,
        0
      ]
    }
  }
]